trytond/modules/sale_discount/__init__.py
trytond/modules/sale_discount/sale.py
trytond/modules/sale_discount/sale.xml
trytond/modules/sale_discount/tryton.cfg
trytond/modules/sale_discount/locale/fr.po
trytond/modules/sale_discount/tests/__init__.py
trytond/modules/sale_discount/tests/scenario_sale_discount.rst
trytond/modules/sale_discount/tests/test_sale_discount.py
trytond/modules/sale_discount/view/sale_line_form.xml
trytond/modules/sale_discount/view/sale_line_tree.xml
trytond/modules/sale_discount/view/sale_line_tree_sequence.xml
a4t_sale_discount-5.0.2.dist-info/LICENSE
a4t_sale_discount-5.0.2.dist-info/METADATA
a4t_sale_discount-5.0.2.dist-info/WHEEL
a4t_sale_discount-5.0.2.dist-info/entry_points.txt
a4t_sale_discount-5.0.2.dist-info/top_level.txt
a4t_sale_discount-5.0.2.dist-info/RECORD
