Metadata-Version: 2.1
Name: a4t-sale-discount
Version: 5.0.2
Summary: Tryton module for sale: Adds the possibility of making a rebate on the sales lines.
Home-page: http://adiczion.com/
Author: Adiczion
Author-email: support@adiczion.net
License: AGPL-3
Download-URL: https://gitlab.com/ate_modules/a4t-sale_discount
Keywords: tryton sale discount
Platform: UNKNOWN
Classifier: Development Status :: 5 - Production/Stable
Classifier: Environment :: Plugins
Classifier: Framework :: Tryton
Classifier: Intended Audience :: Developers
Classifier: Intended Audience :: Financial and Insurance Industry
Classifier: Intended Audience :: Legal Industry
Classifier: License :: OSI Approved :: GNU General Public License (GPL)
Classifier: Natural Language :: Bulgarian
Classifier: Natural Language :: Catalan
Classifier: Natural Language :: Czech
Classifier: Natural Language :: Dutch
Classifier: Natural Language :: English
Classifier: Natural Language :: French
Classifier: Natural Language :: German
Classifier: Natural Language :: Russian
Classifier: Natural Language :: Spanish
Classifier: Operating System :: OS Independent
Classifier: Programming Language :: Python :: 3.4
Classifier: Programming Language :: Python :: 3.5
Classifier: Programming Language :: Python :: 3.6
Classifier: Programming Language :: Python :: 3.7
Classifier: Programming Language :: Python :: Implementation :: CPython
Classifier: Programming Language :: Python :: Implementation :: PyPy
Classifier: Topic :: Office/Business
Requires-Dist: trytond-sale (<5.1,>=5.0)
Requires-Dist: trytond (<5.1,>=5.0)
